paralleldots/__init__.py
paralleldots/config.py
paralleldots/paralleldots_apis.py
paralleldots/usage.py
ParallelDots-3.2.14.dist-info/METADATA
ParallelDots-3.2.14.dist-info/WHEEL
ParallelDots-3.2.14.dist-info/entry_points.txt
ParallelDots-3.2.14.dist-info/top_level.txt
ParallelDots-3.2.14.dist-info/RECORD
