Metadata-Version: 1.1
Name: ParallelDots
Version: 3.2.14
Summary: Python Wrapper for ParallelDots APIs
Home-page: https://github.com/ParallelDots/ParallelDots-Python-API.git
Author: Ahwan Kumar,Manish Kumar,Vipin Kumar Gupta,Akash Sharma
Author-email: ahwan@paralleldots.com,manish@paralleldots.com,vipin@paralleldots.com,akash@paralleldots.com
License: MIT
Keywords: paralleldots sentiment taxonomy ner semantic similarity deeplearning intent emotion abuse nsfw image visual api phrase text parser popularity target sentiment
Platform: UNKNOWN
Classifier: Development Status :: 5 - Production/Stable
Classifier: Intended Audience :: Developers
Classifier: Topic :: Software Development :: Build Tools
Classifier: License :: OSI Approved :: MIT License
Classifier: Programming Language :: Python :: 2
Classifier: Programming Language :: Python :: 2.6
Classifier: Programming Language :: Python :: 2.7
Classifier: Programming Language :: Python :: 3
Classifier: Programming Language :: Python :: 3.0
Classifier: Programming Language :: Python :: 3.1
Classifier: Programming Language :: Python :: 3.2
Classifier: Programming Language :: Python :: 3.3
Classifier: Programming Language :: Python :: 3.4
Classifier: Programming Language :: Python :: 3.5
Classifier: Topic :: Software Development :: Libraries
Classifier: Topic :: Software Development :: Libraries :: Python Modules
